sotai/__init__.py
sotai/api.py
sotai/constants.py
sotai/data.py
sotai/demo.py
sotai/enums.py
sotai/external.py
sotai/features.py
sotai/models.py
sotai/pipeline.py
sotai/trained_model.py
sotai/training.py
sotai/types.py
sotai/layers/__init__.py
sotai/layers/categorical_calibrator.py
sotai/layers/lattice.py
sotai/layers/linear.py
sotai/layers/numerical_calibrator.py
sotai/utils/__init__.py
sotai/utils/shap_utils.py
sotai-0.6.3.dist-info/LICENSE
sotai-0.6.3.dist-info/METADATA
sotai-0.6.3.dist-info/WHEEL
sotai-0.6.3.dist-info/top_level.txt
sotai-0.6.3.dist-info/RECORD
