Metadata-Version: 2.1
Name: sotai
Version: 0.6.3
Summary: A Python Library For Calibrated Modeling Built With PyTorch
Author-email: SOTAI <support@sotai.ai>
Maintainer-email: SOTAI <support@sotai.ai>
License: MIT
Project-URL: Source, https://github.com/SOTAI-Labs/sotai
Project-URL: Documentation, https://github.com/SOTAI-Labs/sotai/tree/main/docs
Project-URL: Feature Requests, https://github.com/SOTAI-Labs/pytorch-calibrated/issues
Project-URL: Bug Reports, https://github.com/SOTAI-Labs/pytorch-calibrated/issues
Classifier: Development Status :: 5 - Production/Stable
Classifier: Intended Audience :: Developers
Classifier: Intended Audience :: Science/Research
Classifier: License :: OSI Approved :: MIT License
Classifier: Natural Language :: English
Classifier: Programming Language :: Python :: 3 :: Only
Classifier: Programming Language :: Python :: 3.8
Classifier: Programming Language :: Python :: 3.9
Classifier: Programming Language :: Python :: 3.10
Classifier: Topic :: Scientific/Engineering :: Artificial Intelligence
Classifier: Topic :: Software Development :: Libraries :: Python Modules
Requires-Python: <3.11,>=3.8
License-File: LICENSE
Requires-Dist: graphlib-backport >=1.0.3
Requires-Dist: numpy <=1.23.5
Requires-Dist: pandas >=1.5.3
Requires-Dist: pydantic <2.0.0,>=1.10.8
Requires-Dist: torch >=2.0.0
Requires-Dist: torchmetrics >=0.11.4
Requires-Dist: torchvision >=0.15.1
Requires-Dist: tqdm >=4.65.0
Requires-Dist: shap >=0.41.0
Requires-Dist: matplotlib >=3.7.0
Requires-Dist: scipy >=1.7.1
